ralfpt/__init__.py
ralfpt/inpainting.py
ralfpt/saliency_detection.py
ralfpt/transforms.py
ralfpt/typehints.py
ralf_preprocessing_tools-0.1.0.dist-info/LICENSE
ralf_preprocessing_tools-0.1.0.dist-info/METADATA
ralf_preprocessing_tools-0.1.0.dist-info/WHEEL
ralf_preprocessing_tools-0.1.0.dist-info/RECORD
