Metadata-Version: 2.1
Name: ralf-preprocessing-tools
Version: 0.1.0
Summary: 
Author: Shunsuke KITADA
Author-email: shunsuke.kitada.0831@gmail.com
Requires-Python: >=3.10,<4.0
Classifier: Programming Language :: Python :: 3
Classifier: Programming Language :: Python :: 3.10
Classifier: Programming Language :: Python :: 3.11
Classifier: Programming Language :: Python :: 3.12
Provides-Extra: lama
Requires-Dist: opencv-python (>=4.8.0.0)
Requires-Dist: pillow (>=8.0.0)
Requires-Dist: simple-lama-inpainting (>=0.1.2,<0.2.0) ; extra == "lama"
Requires-Dist: transformers[torch] (>=4.6.0)
